timestream_query/QueryUtil.py
timestream_query/__init__.py
timestream_query-1.0.2.dist-info/LICENSE
timestream_query-1.0.2.dist-info/METADATA
timestream_query-1.0.2.dist-info/WHEEL
timestream_query-1.0.2.dist-info/top_level.txt
timestream_query-1.0.2.dist-info/RECORD
