Metadata-Version: 2.1
Name: timestream-query
Version: 1.0.2
Summary: A small utility class to query timestream to object array quickly
Home-page: https://github.com/wjsoft08/timestream-query
Author: Woojin Kang
License: MIT License
Classifier: Development Status :: 1 - Planning
Classifier: Topic :: Utilities
Classifier: Intended Audience :: Education
Classifier: Programming Language :: Python :: 3
Classifier: Programming Language :: Python :: 3.10
Classifier: License :: OSI Approved :: MIT License
Classifier: Operating System :: OS Independent
Requires-Python: >=3.6
License-File: LICENSE
